mrkwatkins/oakemu/__init__.py
mrkwatkins/oakemu/runtimeconfig.json
mrkwatkins/oakemu/assemblies/MrKWatkins.Ast.dll
mrkwatkins/oakemu/assemblies/MrKWatkins.OakAsm.Disassembly.Z80.dll
mrkwatkins/oakemu/assemblies/MrKWatkins.OakAsm.Disassembly.dll
mrkwatkins/oakemu/assemblies/MrKWatkins.OakAsm.Formatting.dll
mrkwatkins/oakemu/assemblies/MrKWatkins.OakAsm.IO.ZXSpectrum.dll
mrkwatkins/oakemu/assemblies/MrKWatkins.OakAsm.IO.dll
mrkwatkins/oakemu/assemblies/MrKWatkins.OakAsm.Z80.dll
mrkwatkins/oakemu/assemblies/MrKWatkins.OakAsm.dll
mrkwatkins/oakemu/assemblies/MrKWatkins.OakCpu.Z80.dll
mrkwatkins/oakemu/assemblies/MrKWatkins.OakEmu.Cpus.Z80.dll
mrkwatkins/oakemu/assemblies/MrKWatkins.OakEmu.Cpus.dll
mrkwatkins/oakemu/assemblies/MrKWatkins.OakEmu.Machines.ZXSpectrum.dll
mrkwatkins/oakemu/assemblies/MrKWatkins.OakEmu.dll
mrkwatkins/oakemu/zxspectrum/__init__.py
mrkwatkins/oakemu/zxspectrum/disposable.py
mrkwatkins/oakemu/zxspectrum/keyboard.py
mrkwatkins/oakemu/zxspectrum/keys.py
mrkwatkins/oakemu/zxspectrum/memory.py
mrkwatkins/oakemu/zxspectrum/registers.py
mrkwatkins/oakemu/zxspectrum/screen.py
mrkwatkins/oakemu/zxspectrum/z80.py
mrkwatkins/oakemu/zxspectrum/zxcolour.py
mrkwatkins/oakemu/zxspectrum/zxspectrum.py
mrkwatkins_oakemu-0.0.30.dist-info/METADATA
mrkwatkins_oakemu-0.0.30.dist-info/WHEEL
mrkwatkins_oakemu-0.0.30.dist-info/licenses/LICENSE
mrkwatkins_oakemu-0.0.30.dist-info/RECORD
