Metadata-Version: 2.4
Name: mrkwatkins-oakemu
Version: 0.0.30
Summary: Python wrappers for the OakEmu project.
Project-URL: Homepage, https://www.mrkwatkins.co.uk
Project-URL: Repository, https://github.com/MrKWatkins/OakEmu-Python
Author-email: MrKWatkins <mrkwatkins@gmail.com>
License-Expression: GPL-3.0-only
License-File: LICENSE
Classifier: Development Status :: 3 - Alpha
Classifier: License :: OSI Approved :: GNU General Public License v3 (GPLv3)
Requires-Python: <3.14,>=3.11
Requires-Dist: pythonnet>=3.0.5
